androidtoast/__init__.py
androidtoast/androidtoast.py
android_toast-0.1.0.dist-info/LICENSE
android_toast-0.1.0.dist-info/METADATA
android_toast-0.1.0.dist-info/WHEEL
android_toast-0.1.0.dist-info/top_level.txt
android_toast-0.1.0.dist-info/RECORD
