Metadata-Version: 2.1
Name: android-toast
Version: 0.1.0
Summary: Native toast for android with python
Home-page: UNKNOWN
Author: Edilson Pineda
Author-email: edilsonpineda011@gmail.com
License: UNKNOWN
Keywords: toast android kivy kivymd Android toast python-for-android python
Platform: UNKNOWN
Classifier: Programming Language :: Python :: 3
Classifier: License :: OSI Approved :: MIT License
Classifier: Operating System :: Android
Requires-Python: >=3
Requires-Dist: pyjnius
